{
  "name": "top-pages-7-days",
  "query": {
    "start-date": "7daysAgo",
    "end-date": "yesterday",
    "dimensions": "ga:hostname,ga:pagePath,ga:pageTitle",
    "metrics": [
      "ga:pageviews",
      "ga:sessions",
      "ga:users",
      "ga:pageviewsPerSession",
      "ga:avgSessionDuration",
      "ga:exits"
    ],
    "sort": [
      "-ga:pageviews"
    ],
    "start-index": 1,
    "max-results": 20,
    "samplingLevel": "HIGHER_PRECISION"
  },
  "meta": {
    "name": "Top Pages (7 Days)",
    "description": "Last week's top 20 pages, measured by page views, for all sites."
  },
  "data": [
    {
      "domain": "pittsburghpa.gov",
      "page": "/joinpghpolice/applying/process.html",
      "page_title": "City of Pittsburgh Police Recruitment - Applying Process",
      "pageviews": "418",
      "visits": "316",
      "users": "292",
      "pageviews_per_session": "1.3227848101265822",
      "avg_session_duration": "86.30379746835443",
      "exits": "281"
    },
    {
      "domain": "pittsburghpa.gov",
      "page": "/joinpghfire/applying/process.html",
      "page_title": "City of Pittsburgh Firefighter Recruitment - Applying Process",
      "pageviews": "194",
      "visits": "149",
      "users": "117",
      "pageviews_per_session": "1.3020134228187918",
      "avg_session_duration": "101.48993288590604",
      "exits": "103"
    },
    {
      "domain": "pittsburghpa.gov",
      "page": "/joinpghpolice/benefits/salary.html",
      "page_title": "City of Pittsburgh Police Recruitment - Salary and Benefits",
      "pageviews": "135",
      "visits": "47",
      "users": "97",
      "pageviews_per_session": "2.872340425531915",
      "avg_session_duration": "129.12765957446808",
      "exits": "45"
    },
    {
      "domain": "pittsburghpa.gov",
      "page": "/joinpghpolice/index.html",
      "page_title": "City of Pittsburgh Police Recruitment",
      "pageviews": "125",
      "visits": "82",
      "users": "85",
      "pageviews_per_session": "1.524390243902439",
      "avg_session_duration": "117.1219512195122",
      "exits": "60"
    },
    {
      "domain": "pittsburghpa.gov",
      "page": "/joinpghfire/benefits/salary.html",
      "page_title": "City of Pittsburgh Firefighter Recruitment - Salary and Benefits",
      "pageviews": "91",
      "visits": "42",
      "users": "59",
      "pageviews_per_session": "2.1666666666666665",
      "avg_session_duration": "85.52380952380952",
      "exits": "38"
    },
    {
      "domain": "pittsburghpa.gov",
      "page": "/joinpghfire/recruitingevents/index.html",
      "page_title": "City of Pittsburgh Firefighter Recruitment - Current Recruiting Events",
      "pageviews": "71",
      "visits": "7",
      "users": "39",
      "pageviews_per_session": "10.142857142857142",
      "avg_session_duration": "78.14285714285714",
      "exits": "40"
    },
    {
      "domain": "pittsburghpa.gov",
      "page": "/joinpghpolice/recruitingevents/index.html",
      "page_title": "City of Pittsburgh Police Recruitment - Current Recruiting Events",
      "pageviews": "65",
      "visits": "5",
      "users": "53",
      "pageviews_per_session": "13.0",
      "avg_session_duration": "56.0",
      "exits": "11"
    },
    {
      "domain": "pittsburghpa.gov",
      "page": "/joinpghpolice/faqs/index.html",
      "page_title": "City of Pittsburgh Police Recruitment - Recruitment FAQ's",
      "pageviews": "63",
      "visits": "25",
      "users": "47",
      "pageviews_per_session": "2.52",
      "avg_session_duration": "316.28",
      "exits": "27"
    },
    {
      "domain": "pittsburghpa.gov",
      "page": "/joinpghpolice/benefits/benefits.html",
      "page_title": "City of Pittsburgh Police Recruitment - Salary and Benefits",
      "pageviews": "52",
      "visits": "4",
      "users": "43",
      "pageviews_per_session": "13.0",
      "avg_session_duration": "2.75",
      "exits": "12"
    },
    {
      "domain": "pittsburghpa.gov",
      "page": "/joinpghpolice/applying/preparation.html",
      "page_title": "City of Pittsburgh Police Recruitment - Preparation Opportunities",
      "pageviews": "42",
      "visits": "2",
      "users": "24",
      "pageviews_per_session": "21.0",
      "avg_session_duration": "0.0",
      "exits": "12"
    },
    {
      "domain": "pittsburghpa.gov",
      "page": "/joinpghpolice/mentors/index.html",
      "page_title": "City of Pittsburgh Police Recruitment - Mentors",
      "pageviews": "42",
      "visits": "7",
      "users": "30",
      "pageviews_per_session": "6.0",
      "avg_session_duration": "54.714285714285715",
      "exits": "13"
    },
    {
      "domain": "pittsburghpa.gov",
      "page": "/joinpghfire/faqs/index.html",
      "page_title": "City of Pittsburgh Firefighter Recruitment - Recruitment FAQ's",
      "pageviews": "39",
      "visits": "5",
      "users": "27",
      "pageviews_per_session": "7.8",
      "avg_session_duration": "21.2",
      "exits": "10"
    },
    {
      "domain": "pittsburghpa.gov",
      "page": "/joinpghpolice/officerdev/promotions.html",
      "page_title": "City of Pittsburgh Police Recruitment - Promotions",
      "pageviews": "37",
      "visits": "2",
      "users": "26",
      "pageviews_per_session": "18.5",
      "avg_session_duration": "13.5",
      "exits": "2"
    },
    {
      "domain": "pittsburghpa.gov",
      "page": "/joinpghpolice/whyserve/index.html",
      "page_title": "City of Pittsburgh Police Recruitment - Why serve?",
      "pageviews": "30",
      "visits": "4",
      "users": "24",
      "pageviews_per_session": "7.5",
      "avg_session_duration": "8.25",
      "exits": "8"
    },
    {
      "domain": "pittsburghpa.gov",
      "page": "/joinpghfire/benefits/benefits.html",
      "page_title": "City of Pittsburgh Firefighter Recruitment - Salary and Benefits",
      "pageviews": "29",
      "visits": "9",
      "users": "26",
      "pageviews_per_session": "3.2222222222222223",
      "avg_session_duration": "52.0",
      "exits": "10"
    },
    {
      "domain": "pittsburghpa.gov",
      "page": "/joinpghpolice/videos/index.html",
      "page_title": "City of Pittsburgh Police Recruitment - Videos",
      "pageviews": "25",
      "visits": "2",
      "users": "20",
      "pageviews_per_session": "12.5",
      "avg_session_duration": "0.0",
      "exits": "11"
    },
    {
      "domain": "pittsburghpa.gov",
      "page": "/joinpghfire/contact/index.html",
      "page_title": "City of Pittsburgh Firefighter Recruitment - Contact Us",
      "pageviews": "15",
      "visits": "4",
      "users": "12",
      "pageviews_per_session": "3.75",
      "avg_session_duration": "10.75",
      "exits": "6"
    },
    {
      "domain": "pittsburghpa.gov",
      "page": "/joinpghpolice/pittsburgh/transition.html",
      "page_title": "City of Pittsburgh Police Recruitment - Transition",
      "pageviews": "15",
      "visits": "1",
      "users": "11",
      "pageviews_per_session": "15.0",
      "avg_session_duration": "0.0",
      "exits": "1"
    },
    {
      "domain": "pittsburghpa.gov",
      "page": "/joinpghpolice/about/overview.html",
      "page_title": "City of Pittsburgh Police Recruitment - Overview",
      "pageviews": "14",
      "visits": "6",
      "users": "7",
      "pageviews_per_session": "2.3333333333333335",
      "avg_session_duration": "2.6666666666666665",
      "exits": "9"
    },
    {
      "domain": "pittsburghpa.gov",
      "page": "/joinpghpolice/about/units.html",
      "page_title": "City of Pittsburgh Police Recruitment - Specialty Units",
      "pageviews": "13",
      "visits": "4",
      "users": "13",
      "pageviews_per_session": "3.25",
      "avg_session_duration": "0.0",
      "exits": "5"
    }
  ],
  "totals": {
    "users": 1052,
    "visits": 723
  },
  "taken_at": "2019-05-14T23:30:19.721Z"
}